LugandaOCR/__init__.py
LugandaOCR/model.py
LugandaOCR/preprocessing.py
LugandaOCR/utils.py
LugandaOCR-1.0.0.dist-info/METADATA
LugandaOCR-1.0.0.dist-info/WHEEL
LugandaOCR-1.0.0.dist-info/top_level.txt
LugandaOCR-1.0.0.dist-info/RECORD
